ocelot/__init__.py
ocelot/collection.py
ocelot/configuration.py
ocelot/errors.py
ocelot/filesystem.py
ocelot/logger.py
ocelot/model.py
ocelot/report.py
ocelot/utils.py
ocelot/bin/__init__.py
ocelot/bin/ocelot_cli.py
ocelot/data/__init__.py
ocelot/data/EcoSpold02.xsd
ocelot/data/EcoSpold02Activity.xsd
ocelot/data/EcoSpold02ChildActivity.xsd
ocelot/data/EcoSpold02ChildDataTypes.xsd
ocelot/data/EcoSpold02ChildFlowData.xsd
ocelot/data/EcoSpold02ChildMetaInformation.xsd
ocelot/data/EcoSpold02DataTypes.xsd
ocelot/data/EcoSpold02FlowData.xsd
ocelot/data/EcoSpold02MetaInformation.xsd
ocelot/data/report-template.jinja2
ocelot/data/rows-ecoinvent.json
ocelot/data/XmlNamespace.xsd
ocelot/data/__pycache__/__init__.cpython-35.pyc
ocelot/io/__init__.py
ocelot/io/cleanup.py
ocelot/io/ecospold2_meta.py
ocelot/io/extract_ecospold2.py
ocelot/io/validate_ecospold2.py
ocelot/transformations/__init__.py
ocelot/transformations/locations.py
ocelot/transformations/parameterization.py
ocelot_lca-0.1.dist-info/DESCRIPTION.rst
ocelot_lca-0.1.dist-info/entry_points.txt
ocelot_lca-0.1.dist-info/METADATA
ocelot_lca-0.1.dist-info/metadata.json
ocelot_lca-0.1.dist-info/RECORD
ocelot_lca-0.1.dist-info/top_level.txt
ocelot_lca-0.1.dist-info/WHEEL
