Metadata-Version: 2.0
Name: ocelot-lca
Version: 0.1
Summary: Open source linking for life cycle assessment
Home-page: https://ocelot.space/
Author: Chris Mutel
Author-email: cmutel@gmail.com
License: Copyright (c) 2016, Paul Scherrer Institut and ecoinvent centre
Requires-Dist: appdirs
Requires-Dist: arrow
Requires-Dist: docopt
Requires-Dist: jinja2
Requires-Dist: lxml
Requires-Dist: psutil
Requires-Dist: pyprind
Requires-Dist: pyrsistent
Requires-Dist: pytest
Requires-Dist: toolz
